openvino_tensorflow/LICENSE
openvino_tensorflow/__init__.py
openvino_tensorflow/libocm.dylib
openvino_tensorflow/libopenvino.2230.dylib
openvino_tensorflow/libopenvino_c.2230.dylib
openvino_tensorflow/libopenvino_intel_cpu_plugin.so
openvino_tensorflow/libopenvino_tensorflow.dylib
openvino_tensorflow/libopenvino_tensorflow_frontend.2230.dylib
openvino_tensorflow/libtbb.dylib
openvino_tensorflow/libtbb_debug.dylib
openvino_tensorflow/libtbb_preview.dylib
openvino_tensorflow/libtbb_preview_debug.dylib
openvino_tensorflow/libtbbmalloc.dylib
openvino_tensorflow/libtbbmalloc_debug.dylib
openvino_tensorflow/libtbbmalloc_proxy.dylib
openvino_tensorflow/libtbbmalloc_proxy_debug.dylib
openvino_tensorflow/libtf_conversion_extensions.dylib
openvino_tensorflow/plugins.xml
openvino_tensorflow-2.3.0.dist-info/METADATA
openvino_tensorflow-2.3.0.dist-info/WHEEL
openvino_tensorflow-2.3.0.dist-info/top_level.txt
openvino_tensorflow-2.3.0.dist-info/RECORD
