Metadata-Version: 2.1
Name: openvino-tensorflow
Version: 2.3.0
Summary: OpenVINO™ integration with TensorFlow
Home-page: https://github.com/openvinotoolkit/openvino_tensorflow
Author: Intel Corporation
License: Apache License, Version 2.0
Platform: Ubuntu 18.04
